[
    {
        "pID": 100,
        "username": "tony fakename",
        "pass": "abcdefghijklmnop",
        "pTurns": 12,
        "pTime": 182155,
        "pWins": 4,
        "pGamesPlayed":100
    },
    {
        "pID": 101,
        "username": "ted fakename",
        "pass": "abcdefghijklmnop",
        "pTurns": 21,
        "pTime": 132155,
        "pWins": 20,
        "pGamesPlayed":23
    },
    {
        "pID": 102,
        "username": "mario fakename",
        "pass": "abcdefghijklmnop",
        "pTurns": 435,
        "pTime": 112155,
        "pWins": 15,
        "pGamesPlayed":234
    },
    {
        "pID": 103,
        "username": "lupe fakename",
        "pass": "abcdefghijklmnop",
        "pTurns": 45,
        "pTime": 102155,
        "pWins": 15,
        "pGamesPlayed":54
    },
    {
        "pID": "104",
        "username": "chris fakename",
        "pass": "abcdefghijklmnop",
        "pTurns": 73,
        "pTime": 100155,
        "pWins": 18,
        "pGamesPlayed":23
    },
    {
        "pID": "105",
        "username": "hunter fakename",
        "pass": "abcdefghijklmnop",
        "pTurns": 745,
        "pTime": 282155,
        "pWins": 7,
        "pGamesPlayed":11
    },
    {
        "pID": "106",
        "username": "nancy fakename",
        "pass": "abcdefghijklmnop",
        "pTurns": 34,
        "pTime": 148155,
        "pWins": 3,
        "pGamesPlayed":35
    },
    {
        "pID": "107",
        "username": "monica fakename",
        "pass": "abcdefghijklmnop",
        "pTurns": 12,
        "pTime": 199155,
        "pWins": 16,
        "pGamesPlayed":52
    },
    {
        "pID": "108",
        "username": "natalie fakename",
        "pass": "abcdefghijklmnop",
        "pTurns": 11,
        "pTime": 144455,
        "pWins": 16,
        "pGamesPlayed":24
    },
    {
        "pID": "109",
        "username": "ronoldo fakename",
        "pass": "abcdefghijklmnop",
        "pTurns": 93,
        "pTime": 126355,
        "pWins": 14,
        "pGamesPlayed":28
    },
    {
        "pID": "110",
        "username": "rafael fakename",
        "pass": "abcdefghijklmnop",
        "pTurns": 52,
        "pTime": 582155,
        "pWins": 3,
        "pGamesPlayed":12
    }
]